kdeLF/kde_fortran.cpython-310-x86_64-linux-gnu.so
kdeLF/test_kdeLF.py
kdeLF/kdeLF.py
kdeLF/__init__.py
kdeLF/examples/data/test_sample.dat
kdeLF.libs/libintlc-4288b807.so.5
kdeLF.libs/libiomp5-c273031f.so
kdeLF.libs/libifcoremt-6f6154a6.so.5
kdeLF.libs/libsvml-86a14aea.so
kdeLF.libs/libifport-09b14e3a.so.5
kdeLF.libs/libimf-5a80a3b3.so
kdeLF-1.0.7.dist-info/WHEEL
kdeLF-1.0.7.dist-info/METADATA
kdeLF-1.0.7.dist-info/top_level.txt
kdeLF-1.0.7.dist-info/RECORD
kdeLF-1.0.7.dist-info/LICENSE.txt
