Metadata-Version: 2.1
Name: kdeLF
Version: 1.0.7
Summary: A flexible method for estimating luminosity functions via Kernel Density Estimation
Home-page: https://github.com/yunzunli/kdeLF
Author: Zunli Yuan
Author-email: yzl@hunnu.edu.cn
Maintainer: Wenjie Wang
Maintainer-email: wangwenjie327@foxmail.com
License: MIT
Platform: UNKNOWN
Requires-Python: >=3.6
License-File: LICENSE.txt
Requires-Dist: astropy
Requires-Dist: corner
Requires-Dist: emcee
Requires-Dist: h5py
Requires-Dist: matplotlib
Requires-Dist: numpy (>=1.13)
Requires-Dist: scipy
Requires-Dist: tqdm
